html_processing/__init__.py
html_processing/connection.py
html_processing/io.py
html_processing/parser.py
html_processing/traversal.py
html_processing/util.py
html_processing-1.1.4.dist-info/LICENSE
html_processing-1.1.4.dist-info/METADATA
html_processing-1.1.4.dist-info/WHEEL
html_processing-1.1.4.dist-info/top_level.txt
html_processing-1.1.4.dist-info/RECORD
